flask_pymongol/__init__.py
Flask_PyMongol-0.1.1.dist-info/LICENCE
Flask_PyMongol-0.1.1.dist-info/METADATA
Flask_PyMongol-0.1.1.dist-info/WHEEL
Flask_PyMongol-0.1.1.dist-info/top_level.txt
Flask_PyMongol-0.1.1.dist-info/RECORD
