Metadata-Version: 2.1
Name: Flask-PyMongol
Version: 0.1.1
Summary: A less is more Pymongo wrapper for Flask
Home-page: https://github.com/upeguiborja/flask-pymongol
Author: Mateo Upegui Borja
Author-email: upeguiborja@gmail.com
License: BSD
Platform: any
Classifier: Environment :: Web Environment
Classifier: Intended Audience :: Developers
Classifier: License :: OSI Approved :: BSD License
Classifier: Operating System :: OS Independent
Classifier: Programming Language :: Python
Classifier: Topic :: Internet :: WWW/HTTP :: Dynamic Content
Classifier: Topic :: Software Development :: Libraries :: Python Modules
Requires-Python: >= 3.6
